<?xml version="1.0"?>
<settings xmlns="http://maven.apache.org/SETTINGS/1.0.0" xmlns:xsi="http://www.w3.org/2001/XMLSchema-instance" xsi:schemaLocation="http://maven.apache.org/SETTINGS/1.0.0                       https://maven.apache.org/xsd/settings-1.0.0.xsd">
  <localRepository>${user.home}/.m2/repository</localRepository>
  <interactiveMode>true</interactiveMode>
  <usePluginRegistry>false</usePluginRegistry>
  <offline>false</offline>
  <servers>
    <server>
      <id>internal-zup</id>
      <username>admin</username>
      <password>qXEcP23Wjt</password>
    </server>
    <server>
      <id>internal-zup2</id>
      <username>admin</username>
      <password>qXEcP23Wjt</password>
    </server>
  </servers>
</settings>
